rasa_ext_plugin/__init__.py
rasa_ext_plugin/core/__init__.py
rasa_ext_plugin/core/tracker_store.py
rasa_ext_plugin-0.0.3.dist-info/LICENSE
rasa_ext_plugin-0.0.3.dist-info/METADATA
rasa_ext_plugin-0.0.3.dist-info/WHEEL
rasa_ext_plugin-0.0.3.dist-info/top_level.txt
rasa_ext_plugin-0.0.3.dist-info/RECORD
