Metadata-Version: 2.1
Name: rasa-ext-plugin
Version: 0.0.3
Summary: Rasa plugins to extend state and store functionalities
Home-page: http://github.com/appliedsoul/rasa_ext_plugin
Author: Noel Gaur
Author-email: noel.gaur@analyticservice.net
License: MIT
Platform: UNKNOWN
Classifier: License :: OSI Approved :: MIT License
Classifier: Programming Language :: Python :: 3
Classifier: Programming Language :: Python :: 3.7
Requires-Dist: rasa
